calcp/__init__.py
calcp/fun.py
calcp-0.0.1.1.dist-info/METADATA
calcp-0.0.1.1.dist-info/WHEEL
calcp-0.0.1.1.dist-info/top_level.txt
calcp-0.0.1.1.dist-info/RECORD
